{"job_1": "https://jobyaari.com/jobdetails/2704", "job_2": "https://jobyaari.com/jobdetails/2705", "job_3": "https://jobyaari.com/jobdetails/2699", "job_4": "https://jobyaari.com/jobdetails/2617", "job_5": "https://jobyaari.com/jobdetails/2629", "job_6": "https://jobyaari.com/jobdetails/2621", "job_7": "https://jobyaari.com/jobdetails/2612", "job_8": "https://jobyaari.com/jobdetails/2579", "job_9": "https://jobyaari.com/jobdetails/2553", "job_10": "https://jobyaari.com/jobdetails/2550", "job_11": "https://jobyaari.com/jobdetails/2536", "job_12": "https://jobyaari.com/jobdetails/2508", "job_13": "https://jobyaari.com/jobdetails/2492", "job_14": "https://jobyaari.com/jobdetails/2404", "job_15": "https://jobyaari.com/jobdetails/2401", "job_16": "https://jobyaari.com/jobdetails/2397", "job_17": "https://jobyaari.com/jobdetails/2285", "job_18": "https://jobyaari.com/jobdetails/2283", "job_19": "https://jobyaari.com/jobdetails/1994", "job_20": "https://jobyaari.com/jobdetails/1856", "job_21": "https://jobyaari.com/jobdetails/2070", "job_22": "https://jobyaari.com/jobdetails/2418", "job_23": "https://jobyaari.com/jobdetails/2419", "job_24": "https://jobyaari.com/jobdetails/2576", "job_25": "https://jobyaari.com/jobdetails/2584", "job_26": "https://jobyaari.com/jobdetails/2594", "job_27": "https://jobyaari.com/jobdetails/2598", "job_28": "https://jobyaari.com/jobdetails/2638", "job_29": "https://jobyaari.com/jobdetails/2650", "job_30": "https://jobyaari.com/jobdetails/2659", "job_31": "https://jobyaari.com/jobdetails/2692"}